[{"__symbolic":"module","version":3,"metadata":{"PaymentComponent":{"__symbolic":"class","decorators":[{"__symbolic":"call","expression":{"__symbolic":"reference","module":"@angular/core","name":"Component"},"arguments":[{"selector":"app-payment","templateUrl":"./payment.component.html","styleUrls":["./payment.component.css"]}]}],"members":{"payform":[{"__symbolic":"property","decorators":[{"__symbolic":"call","expression":{"__symbolic":"reference","module":"@angular/core","name":"ViewChild"},"arguments":["payform"]}]}],"__ctor__":[{"__symbolic":"constructor","parameters":[{"__symbolic":"reference","module":"@angular/router","name":"Router"},{"__symbolic":"reference","module":"@angular/router","name":"ActivatedRoute"}]}],"ngAfterViewInit":[{"__symbolic":"method"}],"ngOnInit":[{"__symbolic":"method"}],"tokenCheck":[{"__symbolic":"method"}],"sub":[{"__symbolic":"method"}],"testCheck":[{"__symbolic":"method"}],"demoSuccess":[{"__symbolic":"method"}]}}}},{"__symbolic":"module","version":1,"metadata":{"PaymentComponent":{"__symbolic":"class","decorators":[{"__symbolic":"call","expression":{"__symbolic":"reference","module":"@angular/core","name":"Component"},"arguments":[{"selector":"app-payment","templateUrl":"./payment.component.html","styleUrls":["./payment.component.css"]}]}],"members":{"payform":[{"__symbolic":"property","decorators":[{"__symbolic":"call","expression":{"__symbolic":"reference","module":"@angular/core","name":"ViewChild"},"arguments":["payform"]}]}],"__ctor__":[{"__symbolic":"constructor","parameters":[{"__symbolic":"reference","module":"@angular/router","name":"Router"},{"__symbolic":"reference","module":"@angular/router","name":"ActivatedRoute"}]}],"ngAfterViewInit":[{"__symbolic":"method"}],"ngOnInit":[{"__symbolic":"method"}],"tokenCheck":[{"__symbolic":"method"}],"sub":[{"__symbolic":"method"}],"testCheck":[{"__symbolic":"method"}],"demoSuccess":[{"__symbolic":"method"}]}}}}]