[{"__symbolic":"module","version":3,"metadata":{"OurPackagesComponent":{"__symbolic":"class","decorators":[{"__symbolic":"call","expression":{"__symbolic":"reference","module":"@angular/core","name":"Component"},"arguments":[{"selector":"app-our-packages","templateUrl":"./our-packages.component.html","styleUrls":["./our-packages.component.css"],"providers":[{"__symbolic":"reference","module":"../book/book.component","name":"BookComponent"}]}]}],"members":{"__ctor__":[{"__symbolic":"constructor","parameters":[{"__symbolic":"reference","module":"@angular/router","name":"Router"},{"__symbolic":"reference","module":"../common/api.service","name":"ApiService"},{"__symbolic":"reference","module":"../book/book.component","name":"BookComponent"},{"__symbolic":"reference","module":"@angular/router","name":"ActivatedRoute"},{"__symbolic":"reference","module":"../app.component","name":"AppComponent"}]}],"ngOnInit":[{"__symbolic":"method"}],"select":[{"__symbolic":"method"}],"searchBasedOnString":[{"__symbolic":"method"}],"contactusSubmit":[{"__symbolic":"method"}],"removeUndefined":[{"__symbolic":"method"}],"getPackages":[{"__symbolic":"method"}],"getPackagesDetails":[{"__symbolic":"method"}],"getTests":[{"__symbolic":"method"}],"addPackageCart":[{"__symbolic":"method"}],"isadded":[{"__symbolic":"method"}],"testQuantPlus":[{"__symbolic":"method"}],"testQuantMinus":[{"__symbolic":"method"}],"getTestQuant":[{"__symbolic":"method"}]}}}},{"__symbolic":"module","version":1,"metadata":{"OurPackagesComponent":{"__symbolic":"class","decorators":[{"__symbolic":"call","expression":{"__symbolic":"reference","module":"@angular/core","name":"Component"},"arguments":[{"selector":"app-our-packages","templateUrl":"./our-packages.component.html","styleUrls":["./our-packages.component.css"],"providers":[{"__symbolic":"reference","module":"../book/book.component","name":"BookComponent"}]}]}],"members":{"__ctor__":[{"__symbolic":"constructor","parameters":[{"__symbolic":"reference","module":"@angular/router","name":"Router"},{"__symbolic":"reference","module":"../common/api.service","name":"ApiService"},{"__symbolic":"reference","module":"../book/book.component","name":"BookComponent"},{"__symbolic":"reference","module":"@angular/router","name":"ActivatedRoute"},{"__symbolic":"reference","module":"../app.component","name":"AppComponent"}]}],"ngOnInit":[{"__symbolic":"method"}],"select":[{"__symbolic":"method"}],"searchBasedOnString":[{"__symbolic":"method"}],"contactusSubmit":[{"__symbolic":"method"}],"removeUndefined":[{"__symbolic":"method"}],"getPackages":[{"__symbolic":"method"}],"getPackagesDetails":[{"__symbolic":"method"}],"getTests":[{"__symbolic":"method"}],"addPackageCart":[{"__symbolic":"method"}],"isadded":[{"__symbolic":"method"}],"testQuantPlus":[{"__symbolic":"method"}],"testQuantMinus":[{"__symbolic":"method"}],"getTestQuant":[{"__symbolic":"method"}]}}}}]